stk/__init__.py
stk/aws_config.py
stk/basic_stack.py
stk/cfn_bucket.py
stk/change_set.py
stk/chdir.py
stk/cli.py
stk/config.py
stk/config_file.py
stk/human_bytes.py
stk/ignore_file.py
stk/interpolated_dict.py
stk/multipart_encoder.py
stk/provider.py
stk/stack.py
stk/stack_delegated_command.py
stk/stack_reference.py
stk/stack_refs.py
stk/stack_waiter.py
stk/template.py
stk/template_command.py
stk/template_helpers.py
stk/template_source.py
stk/util.py
stk/config_cmd/__init__.py
stk/config_cmd/add_template.py
stk/config_cmd/cli.py
stk/config_cmd/init.py
stk/tests/__init__.py
stk/tests/test_aws_config.py
stk/tests/test_cli.py
stk/tests/test_config.py
stk/tests/test_config_file.py
stk/tests/test_deploy_metadata.py
stk/tests/test_provider.py
stk/tests/test_refs.py
stk/tests/test_stack.py
stk/tests/test_template.py
stk/tests/test_template_helpers.py
cfn_stk-0.15.2.dist-info/LICENSE.txt
cfn_stk-0.15.2.dist-info/METADATA
cfn_stk-0.15.2.dist-info/WHEEL
cfn_stk-0.15.2.dist-info/entry_points.txt
cfn_stk-0.15.2.dist-info/top_level.txt
cfn_stk-0.15.2.dist-info/RECORD
