Metadata-Version: 2.1
Name: cfn-stk
Version: 0.15.2
Summary: Opinionated CloudFormation deployments
Home-page: https://github.com/jwoffindin/stk
Author: John Woffindin
Author-email: j.woffindin@gmail.com
Keywords: cloudformation,aws,cfn,cli
Classifier: Programming Language :: Python :: 3
Classifier: License :: OSI Approved :: MIT License
Classifier: Operating System :: OS Independent
Requires-Python: >=3.7
License-File: LICENSE.txt
Requires-Dist: boto3
Requires-Dist: cfn-flip
Requires-Dist: click
Requires-Dist: click-aliases
Requires-Dist: cryptography
Requires-Dist: gitpython
Requires-Dist: giturlparse
Requires-Dist: inquirer
Requires-Dist: jinja2
Requires-Dist: jinja2-strcase
Requires-Dist: pyOpenSSL
Requires-Dist: pyyaml
Requires-Dist: rich
Requires-Dist: setuptools
